setup.py
gaus_bino_probability/Binomialdistribution.py
gaus_bino_probability/Gaussiandistribution.py
gaus_bino_probability/Generaldistribution.py
gaus_bino_probability/__init__.py
gaus_bino_probability.egg-info/PKG-INFO
gaus_bino_probability.egg-info/SOURCES.txt
gaus_bino_probability.egg-info/dependency_links.txt
gaus_bino_probability.egg-info/not-zip-safe
gaus_bino_probability.egg-info/top_level.txt