Metadata-Version: 1.0
Name: gaus-bino-probability
Version: 0.1
Summary: Gaussian And Binomial distributions
Home-page: UNKNOWN
Author: Nishant Gupta
Author-email: UNKNOWN
License: UNKNOWN
Platform: UNKNOWN
